sok_ble/__init__.py
sok_ble/const.py
sok_ble/exceptions.py
sok_ble/sok_bluetooth_device.py
sok_ble/sok_parser.py
sok_ble-0.1.8.dist-info/METADATA
sok_ble-0.1.8.dist-info/WHEEL
sok_ble-0.1.8.dist-info/licenses/LICENSE
sok_ble-0.1.8.dist-info/RECORD
