Metadata-Version: 2.4
Name: sok-ble
Version: 0.1.8
Summary: SOK BLE battery interface library
Project-URL: Homepage, https://github.com/IAmTheMitchell/sok-ble
Project-URL: Bug Tracker, https://github.com/IAmTheMitchell/sok-ble/issues
Project-URL: Changelog, https://github.com/IAmTheMitchell/sok-ble/blob/main/CHANGELOG.md
Author-email: Mitchell Carlson <mitchell.carlson.pro@gmail.com>
License: Apache-2.0
License-File: LICENSE
Classifier: License :: OSI Approved :: Apache Software License
Classifier: Operating System :: OS Independent
Classifier: Programming Language :: Python :: 3
Requires-Python: >=3.11
Requires-Dist: async-timeout>=4.0.3
Requires-Dist: bleak-retry-connector>=3.9.0
Requires-Dist: bleak>=0.22.3
